CHANGES.txt
CHANGESPRE2.txt
DEVELOPER.rst
LICENSE.txt
MANIFEST.in
README.rst
setup.py
versions.cfg
lovely/__init__.py
lovely.pyrest.egg-info/PKG-INFO
lovely.pyrest.egg-info/SOURCES.txt
lovely.pyrest.egg-info/dependency_links.txt
lovely.pyrest.egg-info/namespace_packages.txt
lovely.pyrest.egg-info/not-zip-safe
lovely.pyrest.egg-info/requires.txt
lovely.pyrest.egg-info/top_level.txt
lovely/pyrest/__init__.py
lovely/pyrest/rest.py
lovely/pyrest/tests.py
lovely/pyrest/validation.py
lovely/pyrest/sphinx/__init__.py
lovely/pyrest/sphinx/helpers.py
lovely/pyrest/sphinx/service.py
testing/__init__.py
testing/examples/__init__.py
testing/examples/first_example.py
testing/examples/main.py
testing/examples/sphinx.py