Metadata-Version: 1.1
Name: lovely.pyrest
Version: 2.0.8
Summary: rest framework for pyramids
Home-page: https://github.com/lovelysystems/lovely.pyrest
Author: lovely systems
Author-email: office@lovelysystems.com
License: apache license 2.0
Keywords: pyramid rest framework
Platform: UNKNOWN
Classifier: Programming Language :: Python
